easyinference/__init__.py
easyinference/config.py
easyinference/inference.py
easyinference/cloudsql/__init__.py
easyinference/cloudsql/schema.py
easyinference/cloudsql/table_utils.py
easyvertexinference-1.0.2.dist-info/METADATA
easyvertexinference-1.0.2.dist-info/WHEEL
easyvertexinference-1.0.2.dist-info/top_level.txt
easyvertexinference-1.0.2.dist-info/RECORD
