Metadata-Version: 2.1
Name: easyvertexinference
Version: 1.0.2
Summary: Easy inference using Google's Vertex AI and Gemini models
Home-page: https://github.com/ericzhao28/easyinference
Author: Eric
Author-email: Eric <theeric@google.com>
License: MIT
Project-URL: Homepage, https://github.com/ericzhao28/easyinference
Project-URL: Repository, https://github.com/ericzhao28/easyinference.git
Classifier: Development Status :: 3 - Alpha
Classifier: Intended Audience :: Developers
Classifier: License :: OSI Approved :: MIT License
Classifier: Operating System :: OS Independent
Classifier: Programming Language :: Python :: 3
Classifier: Programming Language :: Python :: 3.8
Classifier: Programming Language :: Python :: 3.9
Classifier: Programming Language :: Python :: 3.10
Classifier: Programming Language :: Python :: 3.11
Requires-Python: >=3.8
Requires-Dist: google-cloud-storage
Requires-Dist: google-cloud-aiplatform
Requires-Dist: cloud-sql-python-connector
Requires-Dist: vertexai
Requires-Dist: python-dotenv
Requires-Dist: asyncio
Requires-Dist: typing
Requires-Dist: google-auth
Requires-Dist: SQLAlchemy
Requires-Dist: aiohttp
Requires-Dist: asyncpg
Requires-Dist: greenlet
Requires-Dist: pg8000
